[
  [
    "help",
    {
      "alias": "help",
      "group": "general",
      "desc": "Xem chi tiết hướng dẫn của một lệnh cụ thể. Ví dụ: /help start"
    }
  ],
  [
    "ping",
    {
      "alias": "ping",
      "group": "general",
      "desc": "This helper bot run"
    }
  ],
  [
    "showuser",
    {
      "alias": "showuser",
      "group": "general",
      "desc": "Xem danh sách người dùng đã kết nối"
    }
  ],
  [
    "start",
    {
      "alias": "start",
      "group": "general",
      "desc": "Giới thiệu bot và liệt kê các lệnh đang có",
      "usage": "/start"
    }
  ]
]